azure/mgmt/communication/__init__.py
azure/mgmt/communication/_communication_service_management_client.py
azure/mgmt/communication/_configuration.py
azure/mgmt/communication/_patch.py
azure/mgmt/communication/_version.py
azure/mgmt/communication/py.typed
azure/mgmt/communication/_utils/__init__.py
azure/mgmt/communication/_utils/serialization.py
azure/mgmt/communication/aio/__init__.py
azure/mgmt/communication/aio/_communication_service_management_client.py
azure/mgmt/communication/aio/_configuration.py
azure/mgmt/communication/aio/_patch.py
azure/mgmt/communication/aio/operations/__init__.py
azure/mgmt/communication/aio/operations/_communication_services_operations.py
azure/mgmt/communication/aio/operations/_domains_operations.py
azure/mgmt/communication/aio/operations/_email_services_operations.py
azure/mgmt/communication/aio/operations/_operations.py
azure/mgmt/communication/aio/operations/_patch.py
azure/mgmt/communication/aio/operations/_sender_usernames_operations.py
azure/mgmt/communication/aio/operations/_smtp_usernames_operations.py
azure/mgmt/communication/aio/operations/_suppression_list_addresses_operations.py
azure/mgmt/communication/aio/operations/_suppression_lists_operations.py
azure/mgmt/communication/models/__init__.py
azure/mgmt/communication/models/_communication_service_management_client_enums.py
azure/mgmt/communication/models/_models_py3.py
azure/mgmt/communication/models/_patch.py
azure/mgmt/communication/operations/__init__.py
azure/mgmt/communication/operations/_communication_services_operations.py
azure/mgmt/communication/operations/_domains_operations.py
azure/mgmt/communication/operations/_email_services_operations.py
azure/mgmt/communication/operations/_operations.py
azure/mgmt/communication/operations/_patch.py
azure/mgmt/communication/operations/_sender_usernames_operations.py
azure/mgmt/communication/operations/_smtp_usernames_operations.py
azure/mgmt/communication/operations/_suppression_list_addresses_operations.py
azure_mgmt_communication-2.2.0.dist-info/licenses/LICENSE
azure_mgmt_communication-2.2.0.dist-info/METADATA
azure_mgmt_communication-2.2.0.dist-info/WHEEL
azure_mgmt_communication-2.2.0.dist-info/top_level.txt
azure_mgmt_communication-2.2.0.dist-info/RECORD
